engrams/__init__.py
engrams-0.0.0.dist-info/WHEEL
engrams-0.0.0.dist-info/entry_points.txt
engrams-0.0.0.dist-info/METADATA
engrams-0.0.0.dist-info/RECORD
