Metadata-Version: 2.3
Name: engrams
Version: 0.0.0
Summary: Memories
Author: Tang Ziya
Author-email: Tang Ziya <tcztzy@gmail.Com>
Requires-Python: >=3.14
